llama_index/readers/sec_filings/__init__.py
llama_index/readers/sec_filings/base.py
llama_index/readers/sec_filings/sec_filings.py
llama_index/readers/sec_filings/utils.py
llama_index/readers/sec_filings/prepline_sec_filings/__init__.py
llama_index/readers/sec_filings/prepline_sec_filings/fetch.py
llama_index/readers/sec_filings/prepline_sec_filings/sec_document.py
llama_index/readers/sec_filings/prepline_sec_filings/sections.py
llama_index/readers/sec_filings/prepline_sec_filings/api/__init__.py
llama_index/readers/sec_filings/prepline_sec_filings/api/app.py
llama_index/readers/sec_filings/prepline_sec_filings/api/section.py
llama_index_readers_sec_filings-0.4.1.dist-info/METADATA
llama_index_readers_sec_filings-0.4.1.dist-info/WHEEL
llama_index_readers_sec_filings-0.4.1.dist-info/licenses/LICENSE
llama_index_readers_sec_filings-0.4.1.dist-info/RECORD
