Metadata-Version: 2.4
Name: llama-index-readers-sec-filings
Version: 0.4.1
Summary: llama-index readers sec_filings integration
Author-email: Your Name <you@example.com>
Maintainer: Athe-kunal
License-Expression: MIT
License-File: LICENSE
Keywords: 10-K,10-Q,SEC Filings,finance
Requires-Python: <4.0,>=3.9
Requires-Dist: faker
Requires-Dist: llama-index-core<0.15,>=0.13.0
Requires-Dist: ratelimit
